.gitignore
.pre-commit-config.yaml
AUTHORS
LICENSE
README.md
pyproject.toml
setup.cfg
setup.py
.github/workflows/pre-commit.yml
.github/workflows/pypi.yml
.github/workflows/pytest.yml
LICENSES/0BSD.txt
LICENSES/Apache-2.0.txt
LICENSES/MIT.txt
cython_linux_usbmon.egg-info/PKG-INFO
cython_linux_usbmon.egg-info/SOURCES.txt
cython_linux_usbmon.egg-info/dependency_links.txt
cython_linux_usbmon.egg-info/entry_points.txt
cython_linux_usbmon.egg-info/requires.txt
cython_linux_usbmon.egg-info/top_level.txt
linux_usbmon/__init__.py
linux_usbmon/_cython.pyi
linux_usbmon/capture.py
linux_usbmon/py.typed
src/linux_usbmon.c
src/linux_usbmon.pyx