Metadata-Version: 2.1
Name: cython-linux-usbmon
Version: 1.1.1
Summary: Linux usbmon capture interface
Home-page: UNKNOWN
Author: Diego Elio Pettenò
Author-email: flameeyes@flameeyes.com
License: Apache-2.0
Platform: UNKNOWN
Classifier: Development Status :: 4 - Beta
Classifier: Environment :: Console
Classifier: Intended Audience :: Developers
Classifier: License :: OSI Approved :: Apache Software License
Classifier: Operating System :: POSIX :: Linux
Classifier: Programming Language :: Python
Classifier: Programming Language :: Python :: 3
Classifier: Topic :: System :: Hardware
Requires-Python: ~=3.7
Provides-Extra: dev
